nr_oai_pmh_harvester/__init__.py
nr_oai_pmh_harvester/config.py
nr_oai_pmh_harvester/endpoint_handlers.py
nr_oai_pmh_harvester/error_handler.py
nr_oai_pmh_harvester/parser.py
nr_oai_pmh_harvester/post_processors.py
nr_oai_pmh_harvester/query.py
nr_oai_pmh_harvester/rules/__init__.py
nr_oai_pmh_harvester/rules/nusl/__init__.py
nr_oai_pmh_harvester/rules/nusl/field001.py
nr_oai_pmh_harvester/rules/nusl/field020.py
nr_oai_pmh_harvester/rules/nusl/field022__a.py
nr_oai_pmh_harvester/rules/nusl/field035.py
nr_oai_pmh_harvester/rules/nusl/field04107.py
nr_oai_pmh_harvester/rules/nusl/field046__j.py
nr_oai_pmh_harvester/rules/nusl/field046__k.py
nr_oai_pmh_harvester/rules/nusl/field24500.py
nr_oai_pmh_harvester/rules/nusl/field24630.py
nr_oai_pmh_harvester/rules/nusl/field24633.py
nr_oai_pmh_harvester/rules/nusl/field260.py
nr_oai_pmh_harvester/rules/nusl/field300.py
nr_oai_pmh_harvester/rules/nusl/field336__a.py
nr_oai_pmh_harvester/rules/nusl/field4900.py
nr_oai_pmh_harvester/rules/nusl/field502__c.py
nr_oai_pmh_harvester/rules/nusl/field520.py
nr_oai_pmh_harvester/rules/nusl/field540.py
nr_oai_pmh_harvester/rules/nusl/field586.py
nr_oai_pmh_harvester/rules/nusl/field598__a.py
nr_oai_pmh_harvester/rules/nusl/field65007.py
nr_oai_pmh_harvester/rules/nusl/field65017.py
nr_oai_pmh_harvester/rules/nusl/field650_7.py
nr_oai_pmh_harvester/rules/nusl/field653.py
nr_oai_pmh_harvester/rules/nusl/field656_7a.py
nr_oai_pmh_harvester/rules/nusl/field7102.py
nr_oai_pmh_harvester/rules/nusl/field7112.py
nr_oai_pmh_harvester/rules/nusl/field720.py
nr_oai_pmh_harvester/rules/nusl/field7201.py
nr_oai_pmh_harvester/rules/nusl/field7731.py
nr_oai_pmh_harvester/rules/nusl/field85640.py
nr_oai_pmh_harvester/rules/nusl/field85642u.py
nr_oai_pmh_harvester/rules/nusl/field909COo.py
nr_oai_pmh_harvester/rules/nusl/field970__a.py
nr_oai_pmh_harvester/rules/nusl/field980__a.py
nr_oai_pmh_harvester/rules/nusl/field996.py
nr_oai_pmh_harvester/rules/nusl/field998.py
techlib_nr_oai_pmh_harvester-1.0.0a12.dist-info/entry_points.txt
techlib_nr_oai_pmh_harvester-1.0.0a12.dist-info/LICENSE
techlib_nr_oai_pmh_harvester-1.0.0a12.dist-info/WHEEL
techlib_nr_oai_pmh_harvester-1.0.0a12.dist-info/METADATA
techlib_nr_oai_pmh_harvester-1.0.0a12.dist-info/RECORD
