Metadata-Version: 2.1
Name: techlib-nr-oai-pmh-harvester
Version: 1.0.0a12
Summary: Czech National Repository oai-pmh-harvester
License: MIT
Keywords: Czech,National,Respository,Invenio,harvester,oai,pmh
Author: Daniel Kopecký
Author-email: Daniel.Kopecky@techlib.cz
Requires-Python: >=3.8,<4.0
Classifier: Development Status :: 3 - Alpha
Classifier: Environment :: Web Environment
Classifier: Intended Audience :: Developers
Classifier: License :: OSI Approved :: MIT License
Classifier: Operating System :: OS Independent
Classifier: Programming Language :: Python
Classifier: Programming Language :: Python :: 3
Classifier: Programming Language :: Python :: 3.10
Classifier: Programming Language :: Python :: 3.8
Classifier: Programming Language :: Python :: 3.9
Classifier: Topic :: Internet :: WWW/HTTP :: Dynamic Content
Classifier: Topic :: Software Development :: Libraries :: Python Modules
Provides-Extra: tests
Requires-Dist: dojson (>=1.4.0,<2.0.0)
Requires-Dist: oarepo-oai-pmh-harvester (>=2.0.0-alpha.13,<3.0.0)
Requires-Dist: oarepo-taxonomies (>=3.0.0a1,<4.0.0)
Requires-Dist: pycountry (>=20.7.3)
Requires-Dist: xmltodict (>=0.12.0,<0.13.0)
